Workbook
Name aporte: 'Self invest'!$D$10
Name patrimonio: 'Self invest'!$D$13
Name percentual_salario: 'Self invest'!$D$6
Name qtd_anos: 'Self invest'!$D$11
Name rendimento_carteira: 'Self invest'!$D$5
Name salario: 'Self invest'!$D$4
Name taxa: 'Self invest'!$D$12

Sheet Self invest
B3: Configurações
B4: Salário | D4: 5000
B5: Rendimento carteira | D5: 0.006
B6: Percentual do salario a investir | D6: 0.15
B7: Sugestão de investimento | D7: =salario*percentual_salario -> 750
B9: Investimento Mensal
B10: Quanto investir por mês? | D10: 750
B11: Por quantos anos? | D11: 5
B12: Taxa de rendimento mensal? | D12: 0.01079
B13: Patrimonio acumulado | D13: =FV(taxa,qtd_anos*12,aporte*-1) -> 62832.685
B14: Diviendos mensais | D14: =patrimonio*1% -> 628.32685
B16: Cenarios | D16: Dividendo
A17: 2 | B17: Quanto em 2 anos | C17: =FV($D$12,$A17*12,$D$10*-1) -> 20420.72 | D17: =C17*rendimento_carteira -> 122.52432
A18: 5 | B18: Quanto em 5 anos | C18: =FV($D$12,$A18*12,$D$10*-1) -> 62832.685 | D18: =C18*rendimento_carteira -> 376.99611
A19: 10 | B19: Quanto em 10 anos | C19: =FV($D$12,$A19*12,$D$10*-1) -> 182463.16 | D19: =C19*rendimento_carteira -> 1094.779
A20: 20 | B20: Quanto em 20 anos | C20: =FV($D$12,$A20*12,$D$10*-1) -> 843898.8 | D20: =C20*rendimento_carteira -> 5063.3928
A21: 30 | B21: Quanto em 30 anos | C21: =FV($D$12,$A21*12,$D$10*-1) -> 3241627.2 | D21: =C21*rendimento_carteira -> 19449.763
B23: Perfil de Investidor | D23: Conservador
B24: Valor a ser investido por mês | D24: =aporte -> 750
B26: Tipo de FII | C26: Percentual sugerido | D26: Valores
B27: PAPEL | C27: =VLOOKUP($D$23&"-"&B27,report!$A$3:$D$21,4,) -> 0.3 | D27: =$D$24*C27 -> 225
B28: TIJOLO | C28: =VLOOKUP($D$23&"-"&B28,report!$A$3:$D$21,4,) -> 0.5 | D28: =$D$24*C28 -> 375
B29: HIBRIDOS | C29: =VLOOKUP($D$23&"-"&B29,report!$A$3:$D$21,4,) -> 0.1 | D29: =$D$24*C29 -> 75
B30: FOFs | C30: =VLOOKUP($D$23&"-"&B30,report!$A$3:$D$21,4,) -> 0.1 | D30: =$D$24*C30 -> 75
B31: DESENVOLVIMENTO | C31: =VLOOKUP($D$23&"-"&B31,report!$A$3:$D$21,4,) -> 0 | D31: =$D$24*C31 -> 0
B32: HOTELARIAS | C32: =VLOOKUP($D$23&"-"&B32,report!$A$3:$D$21,4,) -> 0 | D32: =$D$24*C32 -> 0
D33: =SUM(D27:D32) -> 750

Sheet report
A3: Chave | B3: Perfil | C3: Tipo de FII | D3: Percentual
A4: =B4&"-"&C4 -> Conservador-PAPEL | B4: Conservador | C4: PAPEL | D4: 0.3
A5: =B5&"-"&C5 -> Conservador-TIJOLO | B5: Conservador | C5: TIJOLO | D5: 0.5
A6: =B6&"-"&C6 -> Conservador-HIBRIDOS | B6: Conservador | C6: HIBRIDOS | D6: 0.1
A7: =B7&"-"&C7 -> Conservador-FOFs | B7: Conservador | C7: FOFs | D7: 0.1
A8: =B8&"-"&C8 -> Conservador-DESENVOLVIMENTO | B8: Conservador | C8: DESENVOLVIMENTO | D8: 0
A9: =B9&"-"&C9 -> Conservador-HOTELARIAS | B9: Conservador | C9: HOTELARIAS | D9: 0
A10: =B10&"-"&C10 -> Moderado-PAPEL | B10: Moderado | C10: PAPEL | D10: 0.32
A11: =B11&"-"&C11 -> Moderado-TIJOLO | B11: Moderado | C11: TIJOLO | D11: 0.35
A12: =B12&"-"&C12 -> Moderado-HIBRIDOS | B12: Moderado | C12: HIBRIDOS | D12: 0.08
A13: =B13&"-"&C13 -> Moderado-FOFs | B13: Moderado | C13: FOFs | D13: 0.1
A14: =B14&"-"&C14 -> Moderado-DESENVOLVIMENTO | B14: Moderado | C14: DESENVOLVIMENTO | D14: 0.1
A15: =B15&"-"&C15 -> Moderado-HOTELARIAS | B15: Moderado | C15: HOTELARIAS | D15: 0.05
... A21: =B21&"-"&C21 -> Agressivo-HOTELARIAS | B21: Agressivo | C21: HOTELARIAS | D21: 0.15
